{
  "ServantInjury_BloodLoss": -2075488993,
  "ServantInjury_Cross": 935529743,
  "ServantInjury_ExposedToHolyWater": 186809177,
  "ServantInjury_Farmer": -351784592,
  "ServantInjury_Fight": 1951642705,
  "ServantInjury_Fire": 156962313,
  "ServantInjury_Garlic": 1747602415,
  "ServantInjury_Ratform": -1304230302,
  "ServantInjury_SilverArrow": 1612634118,
  "ServantInjury_StabbedByStake": -421754319,
  "ServantInjury_SunBurned": 685584511,
  "ServantInjury_VampireHunter": 1092922249
}